shift_operation/__init__.py
shift_operation/list_shift_operation.py
listshiftoperationpkg-0.0.1.dist-info/METADATA
listshiftoperationpkg-0.0.1.dist-info/WHEEL
listshiftoperationpkg-0.0.1.dist-info/top_level.txt
listshiftoperationpkg-0.0.1.dist-info/RECORD
